gene_level/__init__.py
gene_level/network.py
sc_utils/__init__.py
sc_utils/cluster.py
sc_utils/pipeline_utils.py
sc_utils/scanpy_utils.py
temporary_projects_brainfo-0.1.dist-info/LICENSE
temporary_projects_brainfo-0.1.dist-info/METADATA
temporary_projects_brainfo-0.1.dist-info/WHEEL
temporary_projects_brainfo-0.1.dist-info/top_level.txt
temporary_projects_brainfo-0.1.dist-info/RECORD
