Metadata-Version: 2.1
Name: temporary_projects_brainfo
Version: 0.1
Summary: A small collective utils for 2nd generation sequencing analysis
Author: Brainfo
Author-email: Brainfo <scilavisher@gmail.com>
Project-URL: Homepage, https://github.com/brainfo/omics_utils
Project-URL: Issues, https://github.com/brainfo/omics_utils/issues
Classifier: Programming Language :: Python :: 3
Classifier: License :: OSI Approved :: MIT License
Classifier: Operating System :: OS Independent
Requires-Python: >=3.8
License-File: LICENSE
